async_strava/__init__.py
async_strava/attributes.py
async_strava/exceptions.py
async_strava/strava.py
strava-0.2.2.dist-info/LICENSE
strava-0.2.2.dist-info/METADATA
strava-0.2.2.dist-info/WHEEL
strava-0.2.2.dist-info/top_level.txt
strava-0.2.2.dist-info/zip-safe
strava-0.2.2.dist-info/RECORD
