Metadata-Version: 2.1
Name: strava
Version: 0.2.2
Summary: Parse https://www.strava.com website using asyncio
Home-page: UNKNOWN
Author: Michael S2pac
Author-email: mixa21.11@mail.ru
License: MIT
Project-URL: Source, https://github.com/mixa2130/strava
Platform: UNKNOWN
Classifier: License :: OSI Approved :: Apache Software License
Classifier: Topic :: Internet
Classifier: Topic :: Software Development
Classifier: Topic :: Software Development :: Libraries
Classifier: Intended Audience :: Developers
Classifier: Natural Language :: English
Classifier: Operating System :: MacOS
Classifier: Operating System :: POSIX
Classifier: Programming Language :: Python
Classifier: Programming Language :: Python :: 3
Classifier: Programming Language :: Python :: 3.6
Classifier: Programming Language :: Python :: 3.7
Classifier: Programming Language :: Python :: 3.8
Classifier: Programming Language :: Python :: Implementation :: CPython
License-File: LICENSE
Requires-Dist: lxml (~=4.6.3)
Requires-Dist: bs4 (~=0.0.1)
Requires-Dist: beautifulsoup4 (~=4.9.3)
Requires-Dist: soupsieve (~=2.2.1)
Requires-Dist: attrs (~=20.3.0)
Requires-Dist: idna (~=2.10)
Requires-Dist: multidict (~=5.1.0)
Requires-Dist: asyncio (~=3.4.3)
Requires-Dist: yarl (~=1.6.3)
Requires-Dist: aiohttp (~=3.7.4.post0)
Requires-Dist: certifi (~=2020.12.5)
Requires-Dist: chardet (~=4.0.0)
Requires-Dist: urllib3 (~=1.26.4)
Requires-Dist: six (~=1.15.0)
Requires-Dist: executing (~=0.5.4)
Requires-Dist: setuptools (~=44.0.0)
Requires-Dist: python-dotenv (~=0.17.0)
Requires-Dist: py (~=1.10.0)
Requires-Dist: toml (~=0.10.2)
Requires-Dist: isort (~=5.8.0)
Requires-Dist: aiomisc (~=13.0.0)
Requires-Dist: astroid (~=2.5.6)
Requires-Dist: mccabe (~=0.6.1)
Requires-Dist: pluggy (~=0.13.1)
Requires-Dist: iniconfig (~=1.1.1)
Requires-Dist: colorlog (~=5.0.1)
Requires-Dist: wrapt (~=1.12.1)
Requires-Dist: coverage (~=5.5)
Requires-Dist: requests (~=2.25.1)
Requires-Dist: docopt (~=0.6.2)
Requires-Dist: pyparsing (~=2.4.7)
Requires-Dist: wheel (~=0.37.0)
Requires-Dist: async-class (==0.3.0)
